{
  "$schema": "https://developer.microsoft.com/json-schemas/fabric/item/graphqlApi/definition/1.0.0/schema.json",
  "datasources": [
    {
      "objects": [
        {
          "IsStoredProcedureQueryNode": true,
          "actions": {
            "Execute": "Enabled"
          },
          "fieldMappings": {},
          "graphqlType": "find_products_api",
          "relationships": [],
          "sourceObject": "dbo.find_products_api",
          "sourceObjectType": "StoredProcedure"
        }
      ],
      "sourceItemId": "b6e921fd-1fc3-8e36-4fc7-db5317de937f",
      "sourceType": "SqlDbNative",
      "sourceWorkspaceId": "00000000-0000-0000-0000-000000000000"
    }
  ]
}